DeepSRRF/DeepSRRF for time benchmark.py
DeepSRRF/DeepSRRF.py
DeepSRRF/__init__.py
DeepSRRF/args.py
DeepSRRF/make_noisy_rf.py
DeepSRRF/template.txt
DeepSRRF/utils.py
DeepSRRF-0.0.37.dist-info/METADATA
DeepSRRF-0.0.37.dist-info/WHEEL
DeepSRRF-0.0.37.dist-info/license.txt
DeepSRRF-0.0.37.dist-info/top_level.txt
DeepSRRF-0.0.37.dist-info/RECORD
