Metadata-Version: 2.1
Name: DeepSRRF
Version: 0.0.37
Summary: A framework for Obtaining and Automating Super Resolution for RF data with Deep Learning Algorithms
Home-page: https://github.com/htemiz/DeepSRRF
Author: Hakan Temiz
Author-email: htemiz@artvin.edu.tr
License: UNKNOWN
Project-URL: Documentation, https://github.com/htemiz/deepsr/tree/master/DeepSRRF/docs
Project-URL: Source, https://github.com/htemiz/deepsr/tree/master/DeepSRRF
Keywords: super resolution deep learning DeepSRRF
Platform: UNKNOWN
Classifier: Programming Language :: Python :: 3
Classifier: License :: OSI Approved :: MIT License
Classifier: Operating System :: OS Independent
Requires-Python: >=3
Requires-Dist: scipy (==1.2.1)
Requires-Dist: pandas
Requires-Dist: h5py
Requires-Dist: matplotlib
Requires-Dist: scikit-image (==0.14.3)
Requires-Dist: scikit-video
Requires-Dist: sporco
Requires-Dist: Pillow
Requires-Dist: sewar
Requires-Dist: openpyxl
Requires-Dist: numpy (>=1.13.3tensorflow-gpu==1.14.0)
Requires-Dist: theano
Requires-Dist: keras (==2.2.4)
Requires-Dist: setuptools (>41.0.0)
Requires-Dist: markdown (>=2.2.0)
Requires-Dist: GraphViz
Requires-Dist: importlib
